{
  "project_info": {
    "project_number": "115486900431",
    "project_id": "oouth-coop",
    "storage_bucket": "oouth-coop.firebasestorage.app"
  },
  "client": [
    {
      "client_info": {
        "mobilesdk_app_id": "1:115486900431:android:001ae4edb3e271b8cf37ba",
        "android_client_info": {
          "package_name": "com.emmaggi.oouthcoop"
        }
      },
      "oauth_client": [],
      "api_key": [
        {
          "current_key": "AIzaSyAINtTWwdWcRw1-9LYqa39IpfJcm0Omod4"
        }
      ],
      "services": {
        "appinvite_service": {
          "other_platform_oauth_client": []
        }
      }
    }
  ],
  "configuration_version": "1"
}